{"id":11402,"name":{"en":"Snowy Blue Suit (M)","ar":"Snowy Blue Suit (M)","br":"Snowy Blue Suit (M)","cns":"Snowy Blue Suit (M)","de":"Snowy Blue Suit (M)","fi":"Snowy Blue Suit (M)","fil":"Snowy Blue Suit (M)","fr":"Snowy Blue Suit (M)","id":"Snowy Blue Suit (M)","it":"Snowy Blue Suit (M)","jp":"Snowy Blue Suit (M)","kr":"Snowy Blue Suit (M)","nl":"Snowy Blue Suit (M)","pl":"Snowy Blue Suit (M)","ru":"Snowy Blue Suit (M)","sp":"Snowy Blue Suit (M)","sw":"Snowy Blue Suit (M)","th":"Snowy Blue Suit (M)","tw":"Snowy Blue Suit (M)","vi":"Snowy Blue Suit (M)"},"description":{"en":"null"},"icon":"mcloxms2302upper-et03.png","level":1,"element":"none","abilities":[{"parameter":"speed","add":2,"rate":true}],"category":"fashion","subcategory":"cloth","rarity":"common","sex":"male","stack":1,"sellPrice":1,"consumable":false,"premium":true,"shining":false,"tradable":true,"deletable":true,"durationRealTime":false,"spawns":[]}