{"id":12226,"name":{"en":"Cacti's Red Suit (M)","ar":"Cacti's Red Suit (M)","br":"Traje Cactos (M) [Vermelho]","cns":"Cacti's Red Suit (M)","de":"Cacti's Red Suit (M)","fi":"Cacti's Red Suit (M)","fil":"Cacti's Red Suit (M)","fr":"Habit de Cactus Rouge (M)","id":"Cacti's Red Suit (M)","it":"Cacti's Red Suit (M)","jp":"サボテンのレッドスーツ(M)","kr":"Cacti's Red Suit (M)","nl":"Cacti's Red Suit (M)","pl":"Cacti's Red Suit (M)","ru":"Cacti's Red Suit (M)","sp":"Traje Cactus Rojo (M)","sw":"Cacti's Red Suit (M)","th":"Cacti's Red Suit (M)","tw":"仙人掌紅衣服（男）","vi":"Cacti's Red Suit (M)"},"description":{"en":"null"},"icon":"mclocti01upper-et04.png","level":1,"element":"none","abilities":[{"parameter":"speed","add":1,"rate":true}],"category":"fashion","subcategory":"cloth","rarity":"common","sex":"male","stack":1,"sellPrice":1,"consumable":false,"premium":true,"shining":false,"tradable":true,"deletable":true,"durationRealTime":false,"spawns":[]}