{"id":12690,"name":{"en":"Pirate (F) Suit","ar":"Pirate (F) Suit","br":"Pirate (F) Suit","cns":"Pirate (F) Suit","de":"Pirate (F) Suit","fi":"Pirate (F) Suit","fil":"Pirate (F) Suit","fr":"Habit de Pirate (F)","id":"Pirate (F) Suit","it":"Pirate (F) Suit","jp":"パイレーツ・スーツ(女の子用)","kr":"Pirate (F) Suit","nl":"Pirate (F) Suit","pl":"Pirate (F) Suit","ru":"Pirate (F) Suit","sp":"Traje Pirata (F)","sw":"Pirate (F) Suit","th":"Pirate (F) Suit","tw":"Pirate (F) Suit","vi":"Pirate (F) Suit"},"description":{"en":"null"},"icon":"fclopirate01upper.png","level":1,"element":"none","category":"fashion","subcategory":"cloth","rarity":"common","sex":"female","stack":1,"sellPrice":1,"consumable":false,"premium":true,"shining":false,"tradable":true,"deletable":true,"durationRealTime":false,"spawns":[]}