{"id":12798,"name":{"en":"Mummy Suit (M)","ar":"Mummy Suit (M)","br":"Traje de Múmia (M)","cns":"Mummy Suit (M)","de":"Mummy Suit (M)","fi":"Mummy Suit (M)","fil":"Mummy Suit (M)","fr":"Corps de Momie (G)","id":"Mummy Suit (M)","it":"Mummy Suit (M)","jp":"ミイラ包帯・スーツ(男の子用)","kr":"Mummy Suit (M)","nl":"Mummy Suit (M)","pl":"Mummy Suit (M)","ru":"Mummy Suit (M)","sp":"Traje Momia (M)","sw":"Mummy Suit (M)","th":"Mummy Suit (M)","tw":"木乃伊衣服（男） ","vi":"Mummy Suit (M)"},"description":{"en":"Mummy suit for Male characters. All the pieces were brought from Egypt.","ar":"Mummy suit for Male characters. All the pieces were brought from Egypt.","br":"Traje de Múmia masculino. Todas as peças foram trazidas do Egito.","cns":"Mummy suit for Male characters. All the pieces were brought from Egypt.","de":"Mummy Suit für männliche Charaktere. Alle Teile wurden aus Ägypten importiert.","fi":"Mummy suit for Male characters. All the pieces were brought from Egypt.","fil":"Mummy suit for Male characters. All the pieces were brought from Egypt.","fr":"Vêtement effrayant de momie pour garçon","id":"Mummy suit untuk karakter Pria. Semua potongan dibawa dari Mesir.","it":"Mummy suit for Male characters. All the pieces were brought from Egypt.","jp":"男性キャラクター用のミイラスーツ。エジプトから持ち込まれたようだ。","kr":"Mummy suit for Male characters. All the pieces were brought from Egypt.","nl":"Mummy suit for Male characters. All the pieces were brought from Egypt.","pl":"Mummy suit for Male characters. All the pieces were brought from Egypt.","ru":"Mummy suit for Male characters. All the pieces were brought from Egypt.","sp":"Traje de Momia para personaje masculino. Todas las partes provienen de Egipto.","sw":"Mummy suit for Male characters. All the pieces were brought from Egypt.","th":"Mummy suitสำหรับตัวละครชาย ชิ้นส่วนทั้งหมดนำมาจากอียิปต์","tw":"埃及木乃伊繃帶製作，男角色使用的衣服","vi":"Mummy suit cho các nhân vật nam. Tất cả các mảnh được mang từ Ai Cập."},"icon":"mclomummy01upper.png","level":1,"element":"none","category":"fashion","subcategory":"cloth","rarity":"common","sex":"male","stack":1,"sellPrice":1,"consumable":false,"premium":true,"shining":false,"tradable":true,"deletable":true,"durationRealTime":false,"spawns":[]}