{"id":12908,"name":{"en":"Shining Oricalkum","ar":"Shining Oricalkum","br":"Shining Oricalkum","cns":"Shining Oricalkum","de":"Shining Oricalkum","fi":"Shining Oricalkum","fil":"Shining Oricalkum","fr":"Orichalque Scintillant","id":"Shining Oricalkum","it":"Shining Oricalkum","jp":"輝くオリハルコン","kr":"Shining Oricalkum","nl":"Shining Oricalkum","pl":"Shining Oricalkum","ru":"Shining Oricalkum","sp":"Oricalco Brillante","sw":"Shining Oricalkum","th":"Shining Oricalkum","tw":"Shining Oricalkum","vi":"Shining Oricalkum"},"description":{"en":"Used when converting regular weapons into Ultimate Weapons.","ar":"Used when converting regular weapons into Ultimate Weapons.","br":"Used when converting regular weapons into Ultimate Weapons.","cns":"Used when converting regular weapons into Ultimate Weapons.","de":"Wird verwendet, wenn normale Waffen in Ultimative Waffen umgewandelt werden.","fi":"Used when converting regular weapons into Ultimate Weapons.","fil":"Used when converting regular weapons into Ultimate Weapons.","fr":"Utilisé pour convertir des armes normales en Armes Ultimes.","id":"Used when converting regular weapons into Ultimate Weapons.","it":"Used when converting regular weapons into Ultimate Weapons.","jp":"通常の武器をアルティマ武器に変換する際に使用します。","kr":"Used when converting regular weapons into Ultimate Weapons.","nl":"Used when converting regular weapons into Ultimate Weapons.","pl":"Used when converting regular weapons into Ultimate Weapons.","ru":"Used when converting regular weapons into Ultimate Weapons.","sp":"Se utiliza al convertir armas normales en armas definitivas.","sw":"Used when converting regular weapons into Ultimate Weapons.","th":"Used when converting regular weapons into Ultimate Weapons.","tw":"Used when converting regular weapons into Ultimate Weapons.","vi":"Used when converting regular weapons into Ultimate Weapons."},"icon":"genmatorichalcum02.png","level":1,"element":"none","category":"material","rarity":"veryrare","stack":999,"sellPrice":125000,"consumable":false,"premium":false,"shining":false,"tradable":true,"deletable":true,"durationRealTime":false,"spawns":[]}