{"id":14079,"name":{"en":"Cake Queen Viridian Suit (F)","ar":"Cake Queen Viridian Suit (F)","br":"Cake Queen Viridian Suit (F)","cns":"Cake Queen Viridian Suit (F)","de":"Cake Queen Viridian Suit (F)","fi":"Cake Queen Viridian Suit (F)","fil":"Cake Queen Viridian Suit (F)","fr":"Habit de la Reine-Gâteau Viride (F)","id":"Cake Queen Viridian Suit (F)","it":"Cake Queen Viridian Suit (F)","jp":"ケーキクイーン ビリジアンスーツ(F)","kr":"Cake Queen Viridian Suit (F)","nl":"Cake Queen Viridian Suit (F)","pl":"Cake Queen Viridian Suit (F)","ru":"Cake Queen Viridian Suit (F)","sp":"Traje Reina Tarta Viridian (F)","sw":"Cake Queen Viridian Suit (F)","th":"Cake Queen Viridian Suit (F)","tw":"Cake Queen Viridian Suit (F)","vi":"Cake Queen Viridian Suit (F)"},"description":{"en":"null"},"icon":"fclocakeupper-et05.png","level":1,"element":"none","abilities":[{"parameter":"speed","add":1,"rate":true}],"category":"fashion","subcategory":"cloth","rarity":"common","sex":"female","stack":1,"sellPrice":1,"consumable":false,"premium":true,"shining":false,"tradable":true,"deletable":true,"durationRealTime":false,"spawns":[]}