{"id":15075,"name":{"en":"White Stripes Pink Suit (M)","ar":"White Stripes Pink Suit (M)","br":"White Stripes Pink Suit (M)","cns":"White Stripes Pink Suit (M)","de":"White Stripes Pink Suit (M)","fi":"White Stripes Pink Suit (M)","fil":"White Stripes Pink Suit (M)","fr":"Habit à Bandes Blanches Rose (M)","id":"White Stripes Pink Suit (M)","it":"White Stripes Pink Suit (M)","jp":"ホワイトストライプスピンクスーツ(M)","kr":"White Stripes Pink Suit (M)","nl":"White Stripes Pink Suit (M)","pl":"White Stripes Pink Suit (M)","ru":"White Stripes Pink Suit (M)","sp":"Traje Rayas Blancas Rosa (M)","sw":"White Stripes Pink Suit (M)","th":"White Stripes Pink Suit (M)","tw":"White Stripes Pink Suit (M)","vi":"White Stripes Pink Suit (M)"},"description":{"en":"null"},"icon":"mclowstp01upper-et04.png","level":1,"element":"none","abilities":[{"parameter":"speed","add":2,"rate":true}],"category":"fashion","subcategory":"cloth","rarity":"common","sex":"male","stack":1,"sellPrice":1,"consumable":false,"premium":true,"shining":false,"tradable":true,"deletable":true,"durationRealTime":false,"spawns":[]}