{"id":17259,"name":{"en":"2023 Summer Purple Shoes (F)","ar":"2023 Summer Purple Shoes (F)","br":"2023 Summer Purple Shoes (F)","cns":"2023 Summer Purple Shoes (F)","de":"2023 Summer Purple Shoes (F)","fi":"2023 Summer Purple Shoes (F)","fil":"2023 Summer Purple Shoes (F)","fr":"Chaussures d'Eté 2023 Violettes (F)","id":"2023 Summer Purple Shoes (F)","it":"2023 Summer Purple Shoes (F)","jp":"2023サマーパープルシューズ(F)","kr":"2023 Summer Purple Shoes (F)","nl":"2023 Summer Purple Shoes (F)","pl":"2023 Summer Purple Shoes (F)","ru":"2023 Summer Purple Shoes (F)","sp":"Zapatos Verano 2023 Lila (F)","sw":"2023 Summer Purple Shoes (F)","th":"2023 Summer Purple Shoes (F)","tw":"2023 Summer Purple Shoes (F)","vi":"2023 Summer Purple Shoes (F)"},"description":{"en":"null"},"icon":"fclousmr01foot-et02.png","level":1,"element":"none","abilities":[{"parameter":"speed","add":3,"rate":true}],"category":"fashion","subcategory":"shoes","rarity":"common","sex":"female","stack":1,"sellPrice":1,"consumable":false,"premium":true,"shining":false,"tradable":true,"deletable":true,"durationRealTime":false,"spawns":[]}