{"id":1803,"name":{"en":"Dark Princess Suit (F)","ar":"Dark Princess Suit (F)","br":"Traje Princesa da Escuridão (F)","cns":"黑暗公主衣（女）","de":"Dark Princess Suit (F)","fi":"Dark Princess Suit (F)","fil":"Dark Princess Suit (F)","fr":"Tenue de la Princesse Noire (F)","id":"Dark Princess Suit (F)","it":"Dark Princess Suit (F)","jp":"ダークプリンセススーツ（女）","kr":"다크 프린세스 슈트 (여)","nl":"Dark Princess Suit (F)","pl":"Dark Princess Suit (F)","ru":"Dark Princess Suit (F)","sp":"Traje Oscuro de Princesa (F)","sw":"Dark Princess Suit (F)","th":"Dark Princess Suit (F)","tw":"闇黑公主衣服(女)","vi":"Dark Princess Suit (F)"},"description":{"en":"null"},"icon":"ffwclook02_upper.png","level":1,"element":"none","category":"fashion","subcategory":"cloth","rarity":"common","sex":"female","stack":1,"sellPrice":1,"consumable":false,"premium":true,"shining":false,"tradable":true,"deletable":true,"durationRealTime":false,"spawns":[]}