{"id":18405,"name":{"en":"Rainbow Effect (10 Minutes)","ar":"Rainbow Effect (10 Minutes)","br":"Rainbow Effect (10 Minutes)","cns":"Rainbow Effect (10 Minutes)","de":"Regenbogen Effekt (10 Minuten)","fi":"Rainbow Effect (10 Minutes)","fil":"Rainbow Effect (10 Minutes)","fr":"Effet Arc-en-Ciel (10 minutes)","id":"Rainbow Effect (10 Minutes)","it":"Rainbow Effect (10 Minutes)","jp":"レインボーエフェクト(10分)","kr":"Rainbow Effect (10 Minutes)","nl":"Rainbow Effect (10 Minutes)","pl":"Rainbow Effect (10 Minutes)","ru":"Rainbow Effect (10 Minutes)","sp":"Efecto Arcoiris (10 Minutos)","sw":"Rainbow Effect (10 Minutes)","th":"Rainbow Effect (10 Minutes)","tw":"Rainbow Effect (10 Minutes)","vi":"Rainbow Effect (10 Minutes)"},"description":{"en":"A cute Rainbow aura will appear on your character. Lasts 10 minutes. It can be accumulated to increase its duration.","ar":"A cute Rainbow aura will appear on your character. Lasts 10 minutes. It can be accumulated to increase its duration.","br":"A cute Rainbow aura will appear on your character. Lasts 10 minutes. It can be accumulated to increase its duration.","cns":"A cute Rainbow aura will appear on your character. Lasts 10 minutes. It can be accumulated to increase its duration.","de":"Eine niedliche Regenbogenaura erscheint auf deinem Charakter. Hält 10 Minuten an. Sie kann akkumuliert werden, um ihre Dauer zu verlängern.","fi":"A cute Rainbow aura will appear on your character. Lasts 10 minutes. It can be accumulated to increase its duration.","fil":"A cute Rainbow aura will appear on your character. Lasts 10 minutes. It can be accumulated to increase its duration.","fr":"Une aura arc-en-ciel apparaîtra sur votre personnage. Dure 10 minutes et peut être cumulé pour augmenter la durée.","id":"A cute Rainbow aura will appear on your character. Lasts 10 minutes. It can be accumulated to increase its duration.","it":"A cute Rainbow aura will appear on your character. Lasts 10 minutes. It can be accumulated to increase its duration.","jp":"可愛いレインボーオーラがキャラクターに現れます。所要時間は10分。蓄積することで持続時間を延ばすことができます。","kr":"A cute Rainbow aura will appear on your character. Lasts 10 minutes. It can be accumulated to increase its duration.","nl":"A cute Rainbow aura will appear on your character. Lasts 10 minutes. It can be accumulated to increase its duration.","pl":"A cute Rainbow aura will appear on your character. Lasts 10 minutes. It can be accumulated to increase its duration.","ru":"A cute Rainbow aura will appear on your character. Lasts 10 minutes. It can be accumulated to increase its duration.","sp":"Un lindo Arcoiris aparecerá sobre tu personaje. Dura 10 minutos. Se puede acumular su duración.","sw":"A cute Rainbow aura will appear on your character. Lasts 10 minutes. It can be accumulated to increase its duration.","th":"A cute Rainbow aura will appear on your character. Lasts 10 minutes. It can be accumulated to increase its duration.","tw":"A cute Rainbow aura will appear on your character. Lasts 10 minutes. It can be accumulated to increase its duration.","vi":"A cute Rainbow aura will appear on your character. Lasts 10 minutes. It can be accumulated to increase its duration."},"icon":"syssysglowrainbow.png","level":1,"element":"none","duration":600,"category":"buff","subcategory":"glow","rarity":"common","stack":999,"sellPrice":1,"consumable":true,"premium":true,"shining":false,"tradable":true,"deletable":true,"durationRealTime":true,"spawns":[]}