{"id":247,"name":{"en":"Green Trillipy Shell","ar":"Green Trillipy Shell","br":"Concha de Trillipy Verde","cns":"绿色蜥蜴的背甲","de":"Green Trilipy Shell","fi":"Green Trillipy Shell","fil":"Green Trillipy Shell","fr":"Carapace de Trillipy Verdâtre","id":"Green Trillipy Shell","it":"Green Trillipy Shell","jp":"グリーントリルピの甲羅","kr":"그린트릴리피의등갑","nl":"Green Trillipy Shell","pl":"Green Trillipy Shell","ru":"Панцирь зеленого хватоглота","sp":"Caparazón de Trillipy Verde","sw":"Green Trillipy Shell","th":"Green Trillipy Shell","tw":"綠色毒甲蜈蚣的背甲","vi":"Green Trillipy Shell"},"description":{"en":"Quest item that drops from Green Trillipy.","ar":"Quest item that drops from Green Trillipy.","br":"Uma concha rígida de Trillipy Verde.","cns":"绿色毒甲蜥蜴的背甲","de":"(Questitem) Shell of Green Trilipy","fi":"Quest item that drops from Green Trillipy.","fil":"Quest item that drops from Green Trillipy.","fr":"Carapace appartenant à un Trillipy Verdâtre.","id":"Item quest yang didapat dari Green Trillipy.","it":"Quest item that drops from Green Trillipy.","jp":"グリーントリルピの甲羅。グリーントリルピからドロップするクエストアイテム。","kr":"그린 트릴리피의 등갑","nl":"Quest item that drops from Green Trillipy.","pl":"Quest item that drops from Green Trillipy.","ru":"Ключевой предмет. Его можно добыть, охотясь на зеленых хватоглотов.","sp":"Caparazón de un Trillipy Verde.","sw":"Quest item that drops from Green Trillipy.","th":"Quest itemที่ดรอปจาก Green Trillipy","tw":"[戰利品]綠色毒甲蜈蚣的背甲","vi":"Vật phẩm nhiệm vụ rơi ra từ Green Trillipy."},"icon":"gengemtrilipy1.png","level":1,"element":"none","category":"booty","rarity":"common","stack":9999,"sellPrice":2242,"guildContribution":44,"consumable":false,"premium":false,"shining":false,"tradable":true,"deletable":true,"durationRealTime":false,"spawns":[]}