{"id":4152,"name":{"en":"Destroyed Typhoon","ar":"Destroyed Typhoon","br":"Destroyed Typhoon","cns":"Destroyed Typhoon","de":"Destroyed Yoyo of Hernes","fi":"Destroyed Typhoon","fil":"Destroyed Typhoon","fr":"Typhon Détruit","id":"Destroyed Typhoon","it":"Destroyed Typhoon","jp":"破壊されたタイフーン","kr":"Destroyed Typhoon","nl":"Destroyed Typhoon","pl":"Destroyed Typhoon","ru":"Destroyed Typhoon","sp":"Typhoon Destruido","sw":"Destroyed Typhoon","th":"Destroyed Typhoon","tw":"Destroyed Typhoon","vi":"Destroyed Typhoon"},"description":{"en":"This weapon has been damaged beyond repair.","ar":"This weapon has been damaged beyond repair.","br":"This weapon has been damaged beyond repair.","cns":"This weapon has been damaged beyond repair.","de":"Diese Waffe ist nicht mehr zu reparieren.","fi":"This weapon has been damaged beyond repair.","fil":"This weapon has been damaged beyond repair.","fr":"Cette arme a été irrémédiablement endommagée.","id":"This weapon has been damaged beyond repair.","it":"This weapon has been damaged beyond repair.","jp":"この武器は修復不可能なほど損傷しています。","kr":"This weapon has been damaged beyond repair.","nl":"This weapon has been damaged beyond repair.","pl":"This weapon has been damaged beyond repair.","ru":"This weapon has been damaged beyond repair.","sp":"Esta arma ha sufrido daños irreparables.","sw":"This weapon has been damaged beyond repair.","th":"This weapon has been damaged beyond repair.","tw":"This weapon has been damaged beyond repair.","vi":"This weapon has been damaged beyond repair."},"icon":"weayoyhernes-et02.png","class":9098,"level":143,"element":"none","triggerSkill":4774,"triggerSkillProbability":20,"minAttack":307,"maxAttack":309,"category":"weapon","subcategory":"yoyo","rarity":"common","stack":1,"sellPrice":277346,"attackSpeed":"fast","attackSpeedValue":0.075,"attackRange":6,"twoHanded":true,"additionalSkillDamage":0,"ultimateConvertible":false,"consumable":false,"premium":false,"shining":false,"tradable":true,"deletable":true,"durationRealTime":false,"spawns":[]}