{"id":476,"name":{"en":"Heintis Gauntlets","ar":"Heintis Gauntlets","br":"Manoplas Heintis","cns":"海蒂斯手套","de":"Heintis Gauntlets","fi":"Heintis Gauntlets","fil":"Heintis Gauntlets","fr":"Gants Heintis","id":"Heintis Gauntlets","it":"Heintis Gauntlets","jp":"ヘネン・ガントレット","kr":"Heintis Gauntlets","nl":"Heintis Gauntlets","pl":"Heintis Gauntlets","ru":"Heintis Gauntlets","sp":"Guanteletes Heintis","sw":"Heintis Gauntlets","th":"Heintis Gauntlets","tw":"海蒂斯手套 ","vi":"Heintis Gauntlets"},"description":{"en":"null"},"icon":"fjst01hand.png","class":3545,"level":67,"element":"none","minDefense":370,"maxDefense":374,"category":"armor","subcategory":"gauntlet","rarity":"common","sex":"female","stack":1,"buyPrice":964250,"sellPrice":40177,"consumable":false,"premium":false,"shining":false,"tradable":true,"deletable":true,"durationRealTime":false,"transy":4691,"spawns":[]}