{"id":6176,"name":{"en":"Barbecue","ar":"Barbecue","br":"Churrasco","cns":"烤肉","de":"Barbecue","fi":"Barbecue","fil":"Barbecue","fr":"Barbecue","id":"Barbecue","it":"Barbecue","jp":"バーベキュー","kr":"바베큐","nl":"Barbecue","pl":"Mięso z rożna","ru":"Барбекю","sp":"Barbacoa","sw":"Barbecue","th":"Barbecue","tw":"烤乳豬","vi":"Tiệc Nướng"},"description":{"en":"Recovers 160 HP","ar":"Recovers 160 HP","br":"Ao ponto!","cns":"hp恢复160的食物","de":"Nahrung mit 160 HP Regeneration","fi":"Recovers 160 HP","fil":"Recovers 160 HP","fr":"Aliment régénérant 160 PV","id":"Recovers 160 HP","it":"Recovers 160 HP","jp":"HPが160回復する食べ物","kr":"HP를 160 회복시켜주는 음식","nl":"Recovers 160 HP","pl":"Recovers 160 HP","ru":"Recovers 160 HP","sp":"Recupera 160 HP","sw":"Recovers 160 HP","th":"ฟื้นฟู 160 HP","tw":"恢復160 HP","vi":"Recovers 160 HP"},"icon":"genfoocoobarbec.png","level":1,"element":"none","cooldown":1.5,"abilities":[{"parameter":"hp","add":160,"rate":false}],"category":"recovery","subcategory":"food","rarity":"common","stack":9999,"sellPrice":4,"consumable":true,"premium":false,"shining":false,"tradable":true,"deletable":true,"durationRealTime":false,"spawns":[]}