{"id":6278,"name":{"en":"Sege Staff","ar":"Sege Staff","br":"Cajado Sege","cns":"山吉斯法杖","de":"Sege Staff","fi":"Sege Staff","fil":"Sege Staff","fr":"Bâton Sege","id":"Sege Staff","it":"Sege Staff","jp":"セージ・スタッフ","kr":"세지 스태프","nl":"Sege Staff","pl":"Sege Staff","ru":"Посох тиары","sp":"Bastón Sege","sw":"Sege Staff","th":"Sege Staff","tw":"山吉斯權杖","vi":"Sege Staff"},"description":{"en":"null"},"icon":"weastaego.png","class":9581,"level":57,"element":"electricity","minAttack":192,"maxAttack":194,"abilities":[{"parameter":"decreasedcastingtime","add":10,"rate":true}],"category":"weapon","subcategory":"staff","rarity":"uncommon","stack":1,"sellPrice":127750,"attackSpeed":"slow","attackSpeedValue":0.045,"attackRange":10,"twoHanded":true,"additionalSkillDamage":7,"ultimateConvertible":false,"consumable":false,"premium":false,"shining":false,"tradable":true,"deletable":true,"durationRealTime":false,"spawns":[]}