{"id":632,"name":{"en":"Fantasy Towel 4% Purple Set","ar":"Fantasy Towel 4% Purple Set","br":"Fantasy Towel 4% Purple Set","cns":"Fantasy Towel 4% Purple Set","de":"Fantasy Towel 4% Purple Set","fi":"Fantasy Towel 4% Purple Set","fil":"Fantasy Towel 4% Purple Set","fr":"Tenue de Bain Violette 4%","id":"Fantasy Towel 4% Purple Set","it":"Fantasy Towel 4% Purple Set","jp":"ファンタジー・タオル4%パープルセット","kr":"Fantasy Towel 4% Purple Set","nl":"Fantasy Towel 4% Purple Set","pl":"Fantasy Towel 4% Purple Set","ru":"Fantasy Towel 4% Purple Set","sp":"Equipo Toalla Fantasía 4% Violeta","sw":"Fantasy Towel 4% Purple Set","th":"Fantasy Towel 4% Purple Set","tw":"夢幻毛巾 4% 紫色套裝","vi":"Fantasy Towel 4% Purple Set"},"description":{"en":"Select which Gender you want to receive!","ar":"Select which Gender you want to receive!","br":"Selecione o Sexo do conjunto que deseja receber!","cns":"选择你需要的套装性别！","de":"Wähle aus welches Geschlecht du erhalten möchtest!","fi":"Select which Gender you want to receive!","fil":"Select which Gender you want to receive!","fr":"Choisissez le sexe du costume que vous souhaitez recevoir !","id":"Pilih Gender yang ingin Anda terima!","it":"Select which Gender you want to receive!","jp":"受け取りたい性別を選択してください！","kr":"받고 싶은 성별을 고르세요!","nl":"Select which Gender you want to receive!","pl":"Select which Gender you want to receive!","ru":"Select which Gender you want to receive!","sp":"¡Selecciona qué género deseas recibir!","sw":"Select which Gender you want to receive!","th":"เลือกเพศที่คุณต้องการรับ!","tw":"選擇您要接到的性別道具！","vi":"Chọn Giới tính mà bạn muốn nhận!"},"icon":"syssysscrbxluck.png","level":1,"element":"none","category":"pack","subcategory":"selectbox","rarity":"common","stack":1,"sellPrice":1,"consumable":true,"premium":true,"shining":false,"tradable":true,"deletable":true,"durationRealTime":false,"spawns":[]}