{"id":674,"name":{"en":"Tight Boots","ar":"Tight Boots","br":"Botas Tight","cns":"龙葵靴子","de":"Tight Boots","fi":"Tight Boots","fil":"Tight Boots","fr":"Bottes Épiques (F)","id":"Tight Boots","it":"Tight Boots","jp":"タイトラン・ブーツ(F)","kr":"타이런트 부츠(여)","nl":"Tight Boots","pl":"Tight Boots","ru":"Редкие сапожки космического стрелка","sp":"Botas Tight","sw":"Tight Boots","th":"Tight Boots","tw":"泰利特靴子","vi":"Ủng Tight "},"description":{"en":"null"},"icon":"frag05foot.png","class":9295,"level":105,"element":"none","minDefense":347,"maxDefense":349,"category":"armor","subcategory":"boots","rarity":"veryrare","sex":"female","stack":1,"sellPrice":422512,"consumable":false,"premium":false,"shining":false,"tradable":true,"deletable":true,"durationRealTime":false,"transy":3514,"spawns":[]}