{"id":6764,"name":{"en":"Roriyet Yo-Yo","ar":"Roriyet Yo-Yo","br":"Ioiô Roriyet","cns":"罗莉叶飞轮","de":"Roriyet Yo-Yo","fi":"Roriyet Yo-Yo","fil":"Roriyet Yo-Yo","fr":"Yo-yo Roriyet","id":"Roriyet Yo-Yo","it":"Roriyet Yo-Yo","jp":"ロリエット・ヨーヨー","kr":"로리예트 요요","nl":"Roriyet Jo-Jo","pl":"Roriyet Yo-Yo","ru":"Roriyet Yo-Yo","sp":"Yo-Yo Roriyet","sw":"Roriyet Yo-Yo","th":"Roriyet Yo-Yo","tw":"羅里耶溜刃","vi":"Roriyet Yo-Yo"},"description":{"en":"null"},"icon":"weayoyset01.png","class":9098,"level":60,"element":"none","triggerSkill":4774,"triggerSkillProbability":20,"minAttack":208,"maxAttack":212,"abilities":[{"parameter":"hitrate","add":20,"rate":true},{"parameter":"attackspeed","add":10,"rate":true}],"category":"weapon","subcategory":"yoyo","rarity":"uncommon","stack":1,"sellPrice":125000,"attackSpeed":"fast","attackSpeedValue":0.075,"attackRange":6,"twoHanded":true,"additionalSkillDamage":0,"ultimateConvertible":false,"consumable":false,"premium":false,"shining":false,"tradable":true,"deletable":true,"durationRealTime":false,"spawns":[]}