{"id":7044,"name":{"en":"Music Beat Pink Suit (F)","ar":"Music Beat Pink Suit (F)","br":"Traje Batida da Música (F) [Rosa]","cns":"粉色音乐节拍套装 (女)","de":"Music Beat Pink Suit (F)","fi":"Music Beat Pink Suit (F)","fil":"Music Beat Pink Suit (F)","fr":"Costume Music Beat Rose (F)","id":"Music Beat Pink Suit (F)","it":"Music Beat Pink Suit (F)","jp":"ミュージック ビート ピンクスーツ (F)","kr":"Music Beat Pink Suit (F)","nl":"Music Beat Pink Suit (F)","pl":"Music Beat Pink Suit (F)","ru":"Music Beat Pink Suit (F)","sp":"Equipo de Música Beat Rosa (F)","sw":"Music Beat Pink Suit (F)","th":"Music Beat Pink Suit (F)","tw":"音樂節拍粉紅裝（女）","vi":"Music Beat Pink Suit (F)"},"description":{"en":"Music Beat Suit for female characters.","ar":"Music Beat Suit for female characters.","br":"Traje Batida da Música feminino.","cns":"女性角色音乐节拍套装。","de":"Music Beat Suit für weibliche Charaktere. ","fi":"Music Beat Suit for female characters.","fil":"Music Beat Suit for female characters.","fr":"Un Costume Music Beat pour fille.","id":"Music Beat Suit untuk karakter wanita.","it":"Music Beat Suit for female characters.","jp":"女性用ミュージックビートスーツ。","kr":"Music Beat Suit for female characters.","nl":"Music Beat Suit for female characters.","pl":"Music Beat Suit for female characters.","ru":"Music Beat Suit for female characters.","sp":"Equipo de Música Beat (F)","sw":"Music Beat Suit for female characters.","th":"Music Beat Suit สำหรับตัวละครหญิง","tw":"女性角色的音樂節拍服裝。","vi":"Nhạc Beat Suit cho nhân vật nữ."},"icon":"fclombt0101upper.png","level":1,"element":"none","abilities":[{"parameter":"speed","add":3,"rate":true}],"category":"fashion","subcategory":"cloth","rarity":"common","sex":"female","stack":1,"sellPrice":1,"consumable":false,"premium":true,"shining":false,"tradable":true,"deletable":true,"durationRealTime":false,"spawns":[]}