{"id":7901,"name":{"en":"Rudolph Sled","ar":"Rudolph Sled","br":"Trenó de Rudolph","cns":"圣诞雪橇","de":"Rudolph Sled","fi":"Rudolph Sled","fil":"Rudolph Sled","fr":"Traîneau de Lawolf","id":"Rudolph Sled","it":"Rudolph Sled","jp":"サンタのソリ","kr":"Rudolph Sled","nl":"Rudolph Sled","pl":"Rudolph Sled","ru":"Rudolph Sled","sp":"Trineo Rudolph","sw":"Rudolph Sled","th":"Rudolph Sled","tw":"布魯狼雪橇 ","vi":"Rudolph Sled"},"description":{"en":"Spread the Christmas spirit with this sled!","ar":"Spread the Christmas spirit with this sled!","br":"Espalhe o espírito de Natal com este trenó!","cns":"用这款雪橇传播圣诞精神！","de":"Der Schlitten vom Weihnachtsmann. Frisch vom Nordpol eingeflogen.","fi":"Spread the Christmas spirit with this sled!","fil":"Spread the Christmas spirit with this sled!","fr":"Répandez l'esprit de Noël avec ce traîneau magique volant tiré par un Lawolf !","id":"Sebarkan semangat Natal dengan kereta luncur ini!","it":"Spread the Christmas spirit with this sled!","jp":"はっしれソリよ～♪風のように～♪このソリでクリスマス気分になろう！HEY!","kr":"이 썰매로 크리스마스 분위기를 전파하세요!","nl":"Spread the Christmas spirit with this sled!","pl":"Spread the Christmas spirit with this sled!","ru":"Spread the Christmas spirit with this sled!","sp":"¡Difunde el espíritu navideño con este trineo!","sw":"Spread the Christmas spirit with this sled!","th":"กระจายจิตวิญญาณแห่งคริสต์มาสด้วยเลื่อนนี้!","tw":"傳播聖誕精神雪橇！","vi":"Hãy lan tỏa tinh thần Giáng sinh với chiếc xe trượt tuyết này!"},"icon":"sysevesled.png","level":1,"element":"none","casting":2.5,"category":"flying","subcategory":"board","rarity":"common","stack":1,"sellPrice":1,"flightSpeed":66,"consumable":false,"premium":true,"shining":false,"tradable":true,"deletable":true,"durationRealTime":false,"spawns":[]}