{"id":8762,"name":{"en":"High Elemental Card Box","ar":"High Elemental Card Box","br":"Caixa Superior de Cartas Elementais","cns":"高级属性卡礼盒","de":"High Elemental Card Box","fi":"High Elemental Card Box","fil":"High Elemental Card Box","fr":"Boîte de Haute Carte Élémentale","id":"High Elemental Card Box","it":"High Elemental Card Box","jp":"高レベル属性カードボックス","kr":"고급 엘리멘터 카드 박스","nl":"High Elemental Card Box","pl":"High Elemental Card Box","ru":"High Elemental Card Box","sp":"Caja de Carta Elemental Superior","sw":"High Elemental Card Box","th":"High Elemental Card Box","tw":"高等屬性卡片箱","vi":"Hộp thẻ nguyên tố cao"},"description":{"en":"Contains 5x all elemental cards for upgrades from +6 to +10.","ar":"Contains 5x all elemental cards for upgrades from +6 to +10.","br":"Contém 5 cartas de cada elemento para fortalecimentos de +6 a +10.","cns":"包含用来从+6强化到+10的所有元素卡片各5张。","de":"Enthält alle Elementkarten für +6 bis +10 5-Mal.","fi":"Contains 5x all elemental cards for upgrades from +6 to +10.","fil":"Contains 5x all elemental cards for upgrades from +6 to +10.","fr":"Contient 5 fois chacune des cartes élémentaires de +6 à +10 (liées).","id":"Berisi 5x semua kartu elemen untuk peningkatan dari +6 ke +10.","it":"Contains 5x all elemental cards for upgrades from +6 to +10.","jp":"+6から+10までで使用できる属性強化用カードが全5枚ずつ入っています。","kr":"+6에서 +10으로 업그레이드할 수 있는 모든 엔리멘터 카드 5배 포함.","nl":"Contains 5x all elemental cards for upgrades from +6 to +10.","pl":"Contains 5x all elemental cards for upgrades from +6 to +10.","ru":"Contains 5x all elemental cards for upgrades from +6 to +10.","sp":"Contiene 5x todas las cartas elementales que mejoran de +6 a +10.","sw":"Contains 5x all elemental cards for upgrades from +6 to +10.","th":"ประกอบด้วยการ์ดธาตุทั้งหมด 5x สำหรับการอัปเกรดจาก +6 เป็น +10","tw":"含有+6~+10升級的各屬性5張卡片","vi":"Chứa 5x tất cả các thẻ nguyên tố để nâng cấp từ +6 lên +10."},"icon":"defaultpackbox01.png","level":1,"element":"none","category":"pack","rarity":"common","stack":9,"sellPrice":1,"consumable":true,"premium":false,"shining":false,"tradable":true,"deletable":true,"durationRealTime":false,"spawns":[]}