{"id":9063,"name":{"en":"Golden Cup","ar":"Golden Cup","br":"Cálice Dourado","cns":"黄金杯","de":"Golden Cup","fi":"Golden Cup","fil":"Golden Cup","fr":"Coupe d'Oren","id":"Golden Cup","it":"Golden Cup","jp":"黄金の杯","kr":"황금컵","nl":"Golden Cup","pl":"Golden Cup","ru":"Золотая чаша","sp":"Copa Dorada","sw":"Golden Cup","th":"Golden Cup","tw":"黃金杯","vi":"Golden Cup"},"description":{"en":"Quest item that drops from Wheelem.","ar":"Quest item that drops from Wheelem.","br":"Uma lindo recipiente dourado remanescente do belo Jardim de Rhisis, que terminou em ruínas com a Guerra de Clockworks.","cns":"用黄金制成的杯状雕像。","de":"(Questitem) Eine kleine Tasse aus Gold.","fi":"Quest item that drops from Wheelem.","fil":"Quest item that drops from Wheelem.","fr":"Petite coupe en or.","id":"Item quest yang didapatkan dari Wheelem.","it":"Quest item that drops from Wheelem.","jp":"黄金で作られた小さな杯。ホイールからドロップするクエストアイテム。","kr":"황금으로 만들어진 작은 컵","nl":"Quest item that drops from Wheelem.","pl":"Quest item that drops from Wheelem.","ru":"Ключевой предмет. Его можно добыть, охотясь на ушатронов.","sp":"Escultura con forma de copa que está hecha de oro.","sw":"Quest item that drops from Wheelem.","th":"Quest item ที่ดร็อปจาก Wheelem ","tw":"[戰利品]用黃金製作而成的杯子。","vi":"Vật phẩm nhiệm vụ rơi ra từ Wheelem."},"icon":"gengemgoldcu.png","level":1,"element":"none","category":"booty","rarity":"common","stack":9999,"sellPrice":700,"guildContribution":25,"consumable":false,"premium":false,"shining":false,"tradable":true,"deletable":true,"durationRealTime":false,"spawns":[]}