{"id":9175,"name":{"en":"Winter Wizard Purple Suit (M)","ar":"Winter Wizard Purple Suit (M)","br":"Traje de Feiticeiro do Inverno (M) [Roxo]","cns":"Winter Wizard Purple Suit (M)","de":"Winter Wizard Purple Suit (M)","fi":"Winter Wizard Purple Suit (M)","fil":"Winter Wizard Purple Suit (M)","fr":"Habit de Sorcier de l'Hiver Violet (M)","id":"Winter Wizard Purple Suit (M)","it":"Winter Wizard Purple Suit (M)","jp":"冬の魔法使いパープルスーツ(M)","kr":"Winter Wizard Purple Suit (M)","nl":"Winter Wizard Purple Suit (M)","pl":"Winter Wizard Purple Suit (M)","ru":"Winter Wizard Purple Suit (M)","sp":"Traje Mago de Invierno Lila (M)","sw":"Winter Wizard Purple Suit (M)","th":"Winter Wizard Purple Suit (M)","tw":"冬季巫師紫色衣服（男）","vi":"Winter Wizard Purple Suit (M)"},"description":{"en":"null"},"icon":"mclouxm2201upper-et02.png","level":1,"element":"none","abilities":[{"parameter":"speed","add":3,"rate":true}],"category":"fashion","subcategory":"cloth","rarity":"common","sex":"male","stack":1,"sellPrice":1,"consumable":false,"premium":true,"shining":false,"tradable":true,"deletable":true,"durationRealTime":false,"spawns":[]}