{"id":9242,"name":{"en":"Frog Hat (M)","ar":"Frog Hat (M)","br":"Chapéu de Sapinho (M)","cns":"Kuso青蛙帽(男)","de":"Frog Hat (M)","fi":"Frog Hat (M)","fil":"Frog Hat (M)","fr":"Tête de Grenouille (G)","id":"Frog Hat (M)","it":"Frog Hat (M)","jp":"ケロメット(男の子用)","kr":"개구락지 모자(남)","nl":"Frog Hat (M)","pl":"Frog Hat (M)","ru":"Шапка лягушонка","sp":"Gorro de Rana (M)","sw":"Frog Hat (M)","th":"Frog Hat (M)","tw":"Kuso青蛙帽(男)","vi":"Frog Hat (M)"},"description":{"en":"Frog hat for Male characters","ar":"Frog hat for Male characters","br":"Chapéu de Sapinho para personagens Masculinos","cns":"青蛙造型的帽子","de":"Quak~ Quak~ Lustiger Froschhut für Männer","fi":"Frog hat for Male characters","fil":"Frog hat for Male characters","fr":"Un chapeau de grenouille pour garçon","id":"Topi katak untuk karakter Pria","it":"Frog hat for Male characters","jp":"ヘルメット","kr":"개굴개굴~ 개구락지 모자","nl":"Frog hat for Male characters","pl":"Frog hat for Male characters","ru":"Шапка лягушонка для мадригальца.","sp":"Gorro de Rana para Personajes Masculinos.","sw":"Frog hat for Male characters","th":"Frog hatสำหรับตัวละครชาย","tw":"青蛙造型的帽子","vi":"Mũ ếch cho các nhân vật Nam"},"icon":"mclofrog01hat.png","level":1,"element":"none","category":"fashion","subcategory":"hat","rarity":"common","sex":"male","stack":1,"sellPrice":1,"consumable":false,"premium":true,"shining":false,"tradable":true,"deletable":true,"durationRealTime":false,"spawns":[]}