{"id":9443,"name":{"en":"Kina Gauntlets","ar":"Kina Gauntlets","br":"Manoplas Kina","cns":"星耀手套","de":"Kina Gauntlets","fi":"Kina Gauntlets","fil":"Kina Gauntlets","fr":"Gants Kina","id":"Kina Gauntlets","it":"Kina Gauntlets","jp":"キーナ・ガントレット","kr":"Kina Gauntlets","nl":"Kina Gauntlets","pl":"Kina Gauntlets","ru":"Kina Gauntlets","sp":"Guanteletes Kina","sw":"Kina Gauntlets","th":"Kina Gauntlets","tw":"金娜手套 ","vi":"Kina Gauntlets"},"description":{"en":"null"},"icon":"fass07hand.png","class":8962,"level":60,"element":"none","minDefense":298,"maxDefense":300,"category":"armor","subcategory":"gauntlet","rarity":"uncommon","sex":"female","stack":1,"sellPrice":96500,"consumable":false,"premium":false,"shining":false,"tradable":true,"deletable":true,"durationRealTime":false,"transy":3060,"spawns":[]}