{"id":9652,"name":{"en":"Blue Sailor (F)","ar":"Blue Sailor (F)","br":"Marinheiro Azul (F)","cns":"水蓝海军套装(女)","de":"Blue Sailor (F)","fi":"Blue Sailor (F)","fil":"Blue Sailor (F)","fr":"Tenue Bleue d’Écolière (F)","id":"Blue Sailor (F)","it":"Blue Sailor (F)","jp":"セーラー服セット(チェック)(女の子用)","kr":"세일러(여) 블루","nl":"Blue Sailor (F)","pl":"Blue Sailor (F)","ru":"Голубой матросский комплект (ж)","sp":"Marinera Azul (F)","sw":"Blue Sailor (F)","th":"Blue Sailor (F)","tw":"水藍海軍套裝(女)","vi":"Thủy thủ xanh (F)"},"description":{"en":"Blue Sailor set for Female Characters","ar":"Blue Sailor set for Female Characters","br":"Conjunto Marinheiro Azul para Personagens Femininos","cns":"蓝色水手服(女)套装","de":"Sailor Uniform Blue Set für Frauen","fi":"Blue Sailor set for Female Characters","fil":"Blue Sailor set for Female Characters","fr":"Tenue Bleue d’Écolière (2 pièces).","id":"Blue Sailor set for Wanita Characters","it":"Blue Sailor set for Female Characters","jp":"女の子用のセーラー服セット(チェック)が入っているボックス。","kr":"여성 세일러복 블루 세트","nl":"Blue Sailor set for Female Characters","pl":"Blue Sailor set for Female Characters","ru":"Голубой матросский костюм для мадригалки.","sp":"Conjunto de Marinera Azul para Personajes Femeninos","sw":"Blue Sailor set for Female Characters","th":"Blue Sailor Setสำหรับตัวละครหญิง","tw":"水藍海軍套裝(女)","vi":"Blue Sailor đặt cho các nhân vật nữ"},"icon":"syssysscrbxluck.png","level":1,"element":"none","category":"pack","rarity":"common","stack":1,"sellPrice":1,"consumable":true,"premium":true,"shining":false,"tradable":true,"deletable":true,"durationRealTime":false,"spawns":[]}